[
  {
    "atlantis_top": "Pose",
    "atlantis_prob": 0.9461668133735657,
    "pose_rank": 1,
    "france_top": "Paris",
    "france_prob": 0.6045290231704712,
    "paris_rank": 1,
    "paris_prob": 0.6045290231704712,
    "config": "baseline (04h)",
    "alpha": 0.25,
    "num_layers": 8,
    "orthogonal": false
  },
  {
    "atlantis_top": "Pose",
    "atlantis_prob": 0.9505605101585388,
    "pose_rank": 1,
    "france_top": "Paris",
    "france_prob": 0.4498721659183502,
    "paris_rank": 1,
    "paris_prob": 0.4498721659183502,
    "config": "ortho down, 8L\u00d70.25",
    "alpha": 0.25,
    "num_layers": 8,
    "orthogonal": true
  },
  {
    "atlantis_top": "Pose",
    "atlantis_prob": 0.9700565338134766,
    "pose_rank": 1,
    "france_top": "Paris",
    "france_prob": 0.23031814396381378,
    "paris_rank": 1,
    "paris_prob": 0.23031814396381378,
    "config": "ortho down, 8L\u00d70.35",
    "alpha": 0.35,
    "num_layers": 8,
    "orthogonal": true
  },
  {
    "atlantis_top": "Pose",
    "atlantis_prob": 0.9694406986236572,
    "pose_rank": 1,
    "france_top": "a",
    "france_prob": 0.2892189919948578,
    "paris_rank": 3,
    "paris_prob": 0.10818254202604294,
    "config": "ortho down, 8L\u00d70.50",
    "alpha": 0.5,
    "num_layers": 8,
    "orthogonal": true
  },
  {
    "atlantis_top": "Pose",
    "atlantis_prob": 0.909964382648468,
    "pose_rank": 1,
    "france_top": "Paris",
    "france_prob": 0.46489495038986206,
    "paris_rank": 1,
    "paris_prob": 0.46489495038986206,
    "config": "ortho down, 12L\u00d70.15",
    "alpha": 0.15,
    "num_layers": 12,
    "orthogonal": true
  },
  {
    "atlantis_top": "Pose",
    "atlantis_prob": 0.9667096734046936,
    "pose_rank": 1,
    "france_top": "a",
    "france_prob": 0.3022317588329315,
    "paris_rank": 2,
    "paris_prob": 0.22119003534317017,
    "config": "ortho down, 12L\u00d70.20",
    "alpha": 0.2,
    "num_layers": 12,
    "orthogonal": true
  },
  {
    "atlantis_top": "Pose",
    "atlantis_prob": 0.9735661149024963,
    "pose_rank": 1,
    "france_top": "a",
    "france_prob": 0.3817092776298523,
    "paris_rank": 5,
    "paris_prob": 0.06050055846571922,
    "config": "ortho down, 12L\u00d70.25",
    "alpha": 0.25,
    "num_layers": 12,
    "orthogonal": true
  },
  {
    "atlantis_top": "Pose",
    "atlantis_prob": 0.9114828705787659,
    "pose_rank": 1,
    "france_top": "Paris",
    "france_prob": 0.579253613948822,
    "paris_rank": 1,
    "paris_prob": 0.579253613948822,
    "config": "standard, 12L\u00d70.15",
    "alpha": 0.15,
    "num_layers": 12,
    "orthogonal": false
  }
]